wadl2swagger-0.0.5.dist-info/DESCRIPTION.rst
wadl2swagger-0.0.5.dist-info/entry_points.txt
wadl2swagger-0.0.5.dist-info/METADATA
wadl2swagger-0.0.5.dist-info/metadata.json
wadl2swagger-0.0.5.dist-info/RECORD
wadl2swagger-0.0.5.dist-info/top_level.txt
wadl2swagger-0.0.5.dist-info/WHEEL
wadltools/__init__.py
wadltools/swaggerconverter.py
wadltools/wadl.py
wadltools/wadlcrawler.py
wadltools/cli/__init__.py
wadltools/cli/wadl2swagger.py
wadltools/cli/wadlcrawler.py
