Metadata-Version: 2.0
Name: wadl2swagger
Version: 0.0.5
Summary: Convert WADL to Swagger
Home-page: http://github.com/rackerlabs/wadl2swagger
Author: Max Lincoln
Author-email: mlincoln@thoughtworks.com
License: UNKNOWN
Platform: UNKNOWN
Requires-Dist: wadllib (>=1.3)
Requires-Dist: pyyaml (>=3.0)
Requires-Dist: mechanize (>=0.2)
Requires-Dist: lxml (>=3.4)
